practice/layer0_day04_counter/counter8.sv
module counter8 (
    input  logic       clk,
    input  logic       rst_n,   // async
    input  logic       en,
    input  logic       clr,     // sync
    output logic [7:0] cnt
);
    always_ff @(posedge clk or negedge rst_n) begin
        if (!rst_n) cnt <= 8'd0;
        else if (clr) cnt <= 8'd0;
        else if (en) cnt <= cnt + 8'd1;
    end
endmodule

practice/layer0_day04_counter/tb_counter8.sv
`timescale 1ns/1ps

module tb_counter8;
    logic       clk, rst_n, en, clr;
    logic [7:0] cnt;
    
    counter8 dut (.clk(clk), .rst_n(rst_n), .en(en), .clr(clr), .cnt(cnt));
    
    always #5 clk = ~clk;
    
    initial begin
        $dumpfile("dump.vcd");
        $dumpvars(0, tb_counter8);
        
        clk = 0; rst_n = 0; en = 0; clr = 0;
        #12;
        $display("After async reset:     cnt=%3d (expect 0)", cnt);
        
        rst_n = 1; en = 1; clr = 0; #30;
        $display("After 3 clks with en:  cnt=%3d (expect 3)", cnt);
        
        en = 0; #20;
        $display("After 2 clks en=0:     cnt=%3d (expect 3, hold)", cnt);
        
        en = 1; #50;
        $display("After 5 more clks:     cnt=%3d (expect 8)", cnt);
        
        clr = 1; #10;
        $display("After sync clr:        cnt=%3d (expect 0)", cnt);
        clr = 0;
        
        #40;
        $display("After 4 clks:          cnt=%3d (expect 4)", cnt);
        
        // Async reset: pull rst_n low, give time for propagation
        #3 rst_n = 0;
        #1;
        $display("Async reset mid-clk:   cnt=%3d (expect 0, no clock needed)", cnt);
        
        // Release reset, count from 0
        rst_n = 1; #1;
        en = 1;
        #10;
        $display("After 1 clk post-rst:  cnt=%3d (expect 1)", cnt);
        
        $finish;
    end
endmodule

practice/layer0_day04_counter/dump.vcd
$date
	Thu Apr 23 18:19:44 2026
$end
$version
	Icarus Verilog
$end
$timescale
	1ps
$end
$scope module tb_counter8 $end
$var wire 8 ! cnt [7:0] $end
$var reg 1 " clk $end
$var reg 1 # clr $end
$var reg 1 $ en $end
$var reg 1 % rst_n $end
$scope module dut $end
$var wire 1 " clk $end
$var wire 1 # clr $end
$var wire 1 $ en $end
$var wire 1 % rst_n $end
$var reg 8 & cnt [7:0] $end
$upscope $end
$upscope $end
$enddefinitions $end
$comment Show the parameter values. $end
$dumpall
$end
#0
$dumpvars
b0 &
0%
0$
0#
0"
b0 !
$end
#5000
1"
#10000
0"
#12000
1$
1%
#15000
b1 !
b1 &
1"
#20000
0"
#25000
b10 !
b10 &
1"
#30000
0"
#35000
b11 !
b11 &
1"
#40000
0"
#42000
0$
#45000
1"
#50000
0"
#55000
1"
#60000
0"
#62000
1$
#65000
b100 !
b100 &
1"
#70000
0"
#75000
b101 !
b101 &
1"
#80000
0"
#85000
b110 !
b110 &
1"
#90000
0"
#95000
b111 !
b111 &
1"
#100000
0"
#105000
b1000 !
b1000 &
1"
#110000
0"
#112000
1#
#115000
b0 !
b0 &
1"
#120000
0"
#122000
0#
#125000
b1 !
b1 &
1"
#130000
0"
#135000
b10 !
b10 &
1"
#140000
0"
#145000
b11 !
b11 &
1"
#150000
0"
#155000
b100 !
b100 &
1"
#160000
0"
#165000
b0 !
b0 &
0%
1"
#166000
1%
#170000
0"
#175000
b1 !
b1 &
1"
