practice/layer0_day03_register/reg8.sv
module reg8(
    input logic clk,
    input logic rst_n, en,
    input logic [7:0]d,
    output logic [7:0]q
);
    always_ff @(posedge clk) begin
        if (!rst_n) q <= 8'd0;
        else if(en==1) q <= d;
    end
endmodule

practice/layer0_day03_register/tb_reg8.sv
`timescale 1ns/1ps

module tb_reg8;
    logic       clk, rst_n, en;
    logic [7:0] d, q;
    
    reg8 dut (.clk(clk), .rst_n(rst_n), .en(en), .d(d), .q(q));
    
    // Clock: 10ns period
    always #5 clk = ~clk;
    
    initial begin
        $dumpfile("dump.vcd");
        $dumpvars(0, tb_reg8);
        
        // Init
        clk = 0; rst_n = 0; en = 0; d = 8'hAA;
        #12;  // Hold reset for > 1 clock
        $display("After reset:        q=%h (expect 00)", q);
        
        // Release reset, en=0, d=AA → q should stay 0
        rst_n = 1; en = 0; #10;
        $display("rst_n=1, en=0:      q=%h (expect 00, en disabled)", q);
        
        // Enable write: d=AA → q should become AA
        en = 1; d = 8'hAA; #10;
        $display("en=1, d=AA:         q=%h (expect AA)", q);
        
        // Disable, change d: q should hold AA
        en = 0; d = 8'h55; #10;
        $display("en=0, d=55:         q=%h (expect AA, hold)", q);
        
        // Enable again: q should become 55
        en = 1; #10;
        $display("en=1, d=55:         q=%h (expect 55)", q);
        
        // Sync reset test: pull rst_n low, q clears on next clock edge
        rst_n = 0; #10;
        $display("rst_n=0 (sync):     q=%h (expect 00)", q);
        
        $finish;
    end
endmodule

practice/layer0_day03_register/dump.vcd
$date
	Thu Apr 23 17:51:03 2026
$end
$version
	Icarus Verilog
$end
$timescale
	1ps
$end
$scope module tb_reg8 $end
$var wire 8 ! q [7:0] $end
$var reg 1 " clk $end
$var reg 8 # d [7:0] $end
$var reg 1 $ en $end
$var reg 1 % rst_n $end
$scope module dut $end
$var wire 1 " clk $end
$var wire 8 & d [7:0] $end
$var wire 1 $ en $end
$var wire 1 % rst_n $end
$var reg 8 ' q [7:0] $end
$upscope $end
$upscope $end
$enddefinitions $end
$comment Show the parameter values. $end
$dumpall
$end
#0
$dumpvars
bx '
b10101010 &
0%
0$
b10101010 #
0"
bx !
$end
#5000
b0 !
b0 '
1"
#10000
0"
#12000
1%
#15000
1"
#20000
0"
#22000
1$
#25000
b10101010 !
b10101010 '
1"
#30000
0"
#32000
b1010101 #
b1010101 &
0$
#35000
1"
#40000
0"
#42000
1$
#45000
b1010101 !
b1010101 '
1"
#50000
0"
#52000
0%
#55000
b0 !
b0 '
1"
